{
    "2022-06-04 23:56:00": {},
    "2022-06-04 00:01:00": {},
    "2022-06-04 00:06:00": {},
    "2022-06-04 00:11:00": {},
    "2022-06-04 00:16:00": {},
    "2022-06-04 00:21:00": {},
    "2022-06-04 00:26:00": {},
    "2022-06-04 00:31:00": {},
    "2022-06-04 00:36:00": {},
    "2022-06-04 00:41:00": {},
    "2022-06-04 00:46:00": {},
    "2022-06-04 00:51:00": {},
    "2022-06-04 00:56:00": {
        "weather_code": 804,
        "temperature_celcius": 14.16,
        "dewpoint_celcius": 138.73,
        "1_hour_precipitation_percentage": 0.0,
        "clouds_percentage": 98,
        "relative_humidity_percentage": 69,
        "pressure_hpa": 1020,
        "wind_speed_mps": 4.12,
        "visibility_km": 10.0,
        "sunrise_hour": 3,
        "sunset_hour": 20,
        "1_hour_snow_percentage": 0.0,
        "aqi": 2,
        "pm2_5": 3.56,
        "pm10": 5.23,
        "so2": 1.86,
        "no": 0,
        "no2": 3.9,
        "co": 183.58,
        "o3": 89.41,
        "nh3": 1.43
    },
    "2022-06-04 01:01:00": {
        "weather_code": 804,
        "temperature_celcius": 13.96,
        "dewpoint_celcius": 138.74,
        "1_hour_precipitation_percentage": 0.0,
        "clouds_percentage": 96,
        "relative_humidity_percentage": 70,
        "pressure_hpa": 1020,
        "wind_speed_mps": 4.63,
        "visibility_km": 10.0,
        "sunrise_hour": 3,
        "sunset_hour": 20,
        "1_hour_snow_percentage": 0.0,
        "aqi": 2,
        "pm2_5": 3.56,
        "pm10": 5.23,
        "so2": 1.86,
        "no": 0,
        "no2": 3.9,
        "co": 183.58,
        "o3": 89.41,
        "nh3": 1.43
    },
    "2022-06-04 01:06:00": {
        "weather_code": 804,
        "temperature_celcius": 13.96,
        "dewpoint_celcius": 138.74,
        "1_hour_precipitation_percentage": 0.0,
        "clouds_percentage": 96,
        "relative_humidity_percentage": 70,
        "pressure_hpa": 1020,
        "wind_speed_mps": 4.63,
        "visibility_km": 10.0,
        "sunrise_hour": 3,
        "sunset_hour": 20,
        "1_hour_snow_percentage": 0.0,
        "aqi": 2,
        "pm2_5": 3.56,
        "pm10": 5.23,
        "so2": 1.86,
        "no": 0,
        "no2": 3.9,
        "co": 183.58,
        "o3": 89.41,
        "nh3": 1.43
    },
    "2022-06-04 01:11:00": {
        "weather_code": 804,
        "temperature_celcius": 13.96,
        "dewpoint_celcius": 138.74,
        "1_hour_precipitation_percentage": 0.0,
        "clouds_percentage": 96,
        "relative_humidity_percentage": 70,
        "pressure_hpa": 1020,
        "wind_speed_mps": 4.63,
        "visibility_km": 10.0,
        "sunrise_hour": 3,
        "sunset_hour": 20,
        "1_hour_snow_percentage": 0.0,
        "aqi": 2,
        "pm2_5": 3.56,
        "pm10": 5.23,
        "so2": 1.86,
        "no": 0,
        "no2": 3.9,
        "co": 183.58,
        "o3": 89.41,
        "nh3": 1.43
    },
    "2022-06-04 01:16:00": {
        "weather_code": 804,
        "temperature_celcius": 13.88,
        "dewpoint_celcius": 138.7,
        "1_hour_precipitation_percentage": 0.0,
        "clouds_percentage": 96,
        "relative_humidity_percentage": 70,
        "pressure_hpa": 1020,
        "wind_speed_mps": 4.63,
        "visibility_km": 10.0,
        "sunrise_hour": 3,
        "sunset_hour": 20,
        "1_hour_snow_percentage": 0.0,
        "aqi": 2,
        "pm2_5": 3.56,
        "pm10": 5.23,
        "so2": 1.86,
        "no": 0,
        "no2": 3.9,
        "co": 183.58,
        "o3": 89.41,
        "nh3": 1.43
    },
    "2022-06-04 01:21:00": {
        "weather_code": 804,
        "temperature_celcius": 13.72,
        "dewpoint_celcius": 138.84,
        "1_hour_precipitation_percentage": 0.0,
        "clouds_percentage": 96,
        "relative_humidity_percentage": 72,
        "pressure_hpa": 1020,
        "wind_speed_mps": 4.63,
        "visibility_km": 10.0,
        "sunrise_hour": 3,
        "sunset_hour": 20,
        "1_hour_snow_percentage": 0.0,
        "aqi": 2,
        "pm2_5": 3.56,
        "pm10": 5.23,
        "so2": 1.86,
        "no": 0,
        "no2": 3.9,
        "co": 183.58,
        "o3": 89.41,
        "nh3": 1.43
    },
    "2022-06-04 01:26:00": {
        "weather_code": 804,
        "temperature_celcius": 13.67,
        "dewpoint_celcius": 138.82,
        "1_hour_precipitation_percentage": 0.0,
        "clouds_percentage": 100,
        "relative_humidity_percentage": 72,
        "pressure_hpa": 1020,
        "wind_speed_mps": 4.63,
        "visibility_km": 10.0,
        "sunrise_hour": 3,
        "sunset_hour": 20,
        "1_hour_snow_percentage": 0.0,
        "aqi": 2,
        "pm2_5": 3.56,
        "pm10": 5.23,
        "so2": 1.86,
        "no": 0,
        "no2": 3.9,
        "co": 183.58,
        "o3": 89.41,
        "nh3": 1.43
    },
    "2022-06-04 01:31:00": {
        "weather_code": 804,
        "temperature_celcius": 13.65,
        "dewpoint_celcius": 138.92,
        "1_hour_precipitation_percentage": 0.0,
        "clouds_percentage": 100,
        "relative_humidity_percentage": 73,
        "pressure_hpa": 1020,
        "wind_speed_mps": 4.63,
        "visibility_km": 10.0,
        "sunrise_hour": 3,
        "sunset_hour": 20,
        "1_hour_snow_percentage": 0.0,
        "aqi": 2,
        "pm2_5": 3.56,
        "pm10": 5.23,
        "so2": 1.86,
        "no": 0,
        "no2": 3.9,
        "co": 183.58,
        "o3": 89.41,
        "nh3": 1.43
    },
    "2022-06-04 01:36:00": {
        "weather_code": 804,
        "temperature_celcius": 13.61,
        "dewpoint_celcius": 138.9,
        "1_hour_precipitation_percentage": 0.0,
        "clouds_percentage": 100,
        "relative_humidity_percentage": 73,
        "pressure_hpa": 1020,
        "wind_speed_mps": 4.63,
        "visibility_km": 10.0,
        "sunrise_hour": 3,
        "sunset_hour": 20,
        "1_hour_snow_percentage": 0.0,
        "aqi": 2,
        "pm2_5": 5.29,
        "pm10": 8.14,
        "so2": 2.03,
        "no": 0,
        "no2": 3.34,
        "co": 185.25,
        "o3": 94.41,
        "nh3": 0.94
    },
    "2022-06-04 01:41:00": {
        "weather_code": 804,
        "temperature_celcius": 13.55,
        "dewpoint_celcius": 138.87,
        "1_hour_precipitation_percentage": 0.0,
        "clouds_percentage": 100,
        "relative_humidity_percentage": 73,
        "pressure_hpa": 1020,
        "wind_speed_mps": 4.63,
        "visibility_km": 10.0,
        "sunrise_hour": 3,
        "sunset_hour": 20,
        "1_hour_snow_percentage": 0.0,
        "aqi": 2,
        "pm2_5": 5.29,
        "pm10": 8.14,
        "so2": 2.03,
        "no": 0,
        "no2": 3.34,
        "co": 185.25,
        "o3": 94.41,
        "nh3": 0.94
    },
    "2022-06-04 01:46:00": {
        "weather_code": 804,
        "temperature_celcius": 13.53,
        "dewpoint_celcius": 138.86,
        "1_hour_precipitation_percentage": 0.0,
        "clouds_percentage": 100,
        "relative_humidity_percentage": 73,
        "pressure_hpa": 1020,
        "wind_speed_mps": 4.63,
        "visibility_km": 10.0,
        "sunrise_hour": 3,
        "sunset_hour": 20,
        "1_hour_snow_percentage": 0.0,
        "aqi": 2,
        "pm2_5": 5.29,
        "pm10": 8.14,
        "so2": 2.03,
        "no": 0,
        "no2": 3.34,
        "co": 185.25,
        "o3": 94.41,
        "nh3": 0.94
    },
    "2022-06-04 01:51:00": {
        "weather_code": 804,
        "temperature_celcius": 13.57,
        "dewpoint_celcius": 138.76,
        "1_hour_precipitation_percentage": 0.0,
        "clouds_percentage": 100,
        "relative_humidity_percentage": 72,
        "pressure_hpa": 1020,
        "wind_speed_mps": 4.63,
        "visibility_km": 10.0,
        "sunrise_hour": 3,
        "sunset_hour": 20,
        "1_hour_snow_percentage": 0.0,
        "aqi": 2,
        "pm2_5": 5.29,
        "pm10": 8.14,
        "so2": 2.03,
        "no": 0,
        "no2": 3.34,
        "co": 185.25,
        "o3": 94.41,
        "nh3": 0.94
    },
    "2022-06-04 01:56:00": {
        "weather_code": 804,
        "temperature_celcius": 13.54,
        "dewpoint_celcius": 138.75,
        "1_hour_precipitation_percentage": 0.0,
        "clouds_percentage": 100,
        "relative_humidity_percentage": 72,
        "pressure_hpa": 1020,
        "wind_speed_mps": 4.63,
        "visibility_km": 10.0,
        "sunrise_hour": 3,
        "sunset_hour": 20,
        "1_hour_snow_percentage": 0.0,
        "aqi": 2,
        "pm2_5": 5.29,
        "pm10": 8.14,
        "so2": 2.03,
        "no": 0,
        "no2": 3.34,
        "co": 185.25,
        "o3": 94.41,
        "nh3": 0.94
    },
    "2022-06-04 02:01:00": {
        "weather_code": 804,
        "temperature_celcius": 13.51,
        "dewpoint_celcius": 138.84,
        "1_hour_precipitation_percentage": 0.0,
        "clouds_percentage": 100,
        "relative_humidity_percentage": 73,
        "pressure_hpa": 1020,
        "wind_speed_mps": 4.12,
        "visibility_km": 10.0,
        "sunrise_hour": 3,
        "sunset_hour": 20,
        "1_hour_snow_percentage": 0.0,
        "aqi": 2,
        "pm2_5": 5.29,
        "pm10": 8.14,
        "so2": 2.03,
        "no": 0,
        "no2": 3.34,
        "co": 185.25,
        "o3": 94.41,
        "nh3": 0.94
    },
    "2022-06-04 02:06:00": {
        "weather_code": 804,
        "temperature_celcius": 13.47,
        "dewpoint_celcius": 138.82,
        "1_hour_precipitation_percentage": 0.0,
        "clouds_percentage": 100,
        "relative_humidity_percentage": 73,
        "pressure_hpa": 1020,
        "wind_speed_mps": 4.12,
        "visibility_km": 10.0,
        "sunrise_hour": 3,
        "sunset_hour": 20,
        "1_hour_snow_percentage": 0.0,
        "aqi": 2,
        "pm2_5": 5.29,
        "pm10": 8.14,
        "so2": 2.03,
        "no": 0,
        "no2": 3.34,
        "co": 185.25,
        "o3": 94.41,
        "nh3": 0.94
    },
    "2022-06-04 02:11:00": {
        "weather_code": 804,
        "temperature_celcius": 13.46,
        "dewpoint_celcius": 138.82,
        "1_hour_precipitation_percentage": 0.0,
        "clouds_percentage": 100,
        "relative_humidity_percentage": 73,
        "pressure_hpa": 1020,
        "wind_speed_mps": 4.12,
        "visibility_km": 10.0,
        "sunrise_hour": 3,
        "sunset_hour": 20,
        "1_hour_snow_percentage": 0.0,
        "aqi": 2,
        "pm2_5": 5.29,
        "pm10": 8.14,
        "so2": 2.03,
        "no": 0,
        "no2": 3.34,
        "co": 185.25,
        "o3": 94.41,
        "nh3": 0.94
    },
    "2022-06-04 02:16:00": {
        "weather_code": 804,
        "temperature_celcius": 13.45,
        "dewpoint_celcius": 138.81,
        "1_hour_precipitation_percentage": 0.0,
        "clouds_percentage": 100,
        "relative_humidity_percentage": 73,
        "pressure_hpa": 1020,
        "wind_speed_mps": 4.12,
        "visibility_km": 10.0,
        "sunrise_hour": 3,
        "sunset_hour": 20,
        "1_hour_snow_percentage": 0.0,
        "aqi": 2,
        "pm2_5": 5.29,
        "pm10": 8.14,
        "so2": 2.03,
        "no": 0,
        "no2": 3.34,
        "co": 185.25,
        "o3": 94.41,
        "nh3": 0.94
    },
    "2022-06-04 02:21:00": {
        "weather_code": 804,
        "temperature_celcius": 13.35,
        "dewpoint_celcius": 138.76,
        "1_hour_precipitation_percentage": 0.0,
        "clouds_percentage": 100,
        "relative_humidity_percentage": 73,
        "pressure_hpa": 1020,
        "wind_speed_mps": 4.12,
        "visibility_km": 10.0,
        "sunrise_hour": 3,
        "sunset_hour": 20,
        "1_hour_snow_percentage": 0.0,
        "aqi": 2,
        "pm2_5": 5.29,
        "pm10": 8.14,
        "so2": 2.03,
        "no": 0,
        "no2": 3.34,
        "co": 185.25,
        "o3": 94.41,
        "nh3": 0.94
    },
    "2022-06-04 02:26:00": {
        "weather_code": 804,
        "temperature_celcius": 13.3,
        "dewpoint_celcius": 138.84,
        "1_hour_precipitation_percentage": 0.0,
        "clouds_percentage": 100,
        "relative_humidity_percentage": 74,
        "pressure_hpa": 1020,
        "wind_speed_mps": 4.12,
        "visibility_km": 10.0,
        "sunrise_hour": 3,
        "sunset_hour": 20,
        "1_hour_snow_percentage": 0.0,
        "aqi": 2,
        "pm2_5": 5.29,
        "pm10": 8.14,
        "so2": 2.03,
        "no": 0,
        "no2": 3.34,
        "co": 185.25,
        "o3": 94.41,
        "nh3": 0.94
    },
    "2022-06-04 02:31:00": {
        "weather_code": 804,
        "temperature_celcius": 13.3,
        "dewpoint_celcius": 138.84,
        "1_hour_precipitation_percentage": 0.0,
        "clouds_percentage": 100,
        "relative_humidity_percentage": 74,
        "pressure_hpa": 1020,
        "wind_speed_mps": 6.69,
        "visibility_km": 10.0,
        "sunrise_hour": 3,
        "sunset_hour": 20,
        "1_hour_snow_percentage": 0.0,
        "aqi": 2,
        "pm2_5": 4.83,
        "pm10": 6.96,
        "so2": 1.97,
        "no": 0,
        "no2": 2.91,
        "co": 185.25,
        "o3": 92.98,
        "nh3": 0.77
    },
    "2022-06-04 02:36:00": {
        "weather_code": 804,
        "temperature_celcius": 13.31,
        "dewpoint_celcius": 138.85,
        "1_hour_precipitation_percentage": 0.0,
        "clouds_percentage": 100,
        "relative_humidity_percentage": 74,
        "pressure_hpa": 1020,
        "wind_speed_mps": 6.69,
        "visibility_km": 10.0,
        "sunrise_hour": 3,
        "sunset_hour": 20,
        "1_hour_snow_percentage": 0.0,
        "aqi": 2,
        "pm2_5": 4.83,
        "pm10": 6.96,
        "so2": 1.97,
        "no": 0,
        "no2": 2.91,
        "co": 185.25,
        "o3": 92.98,
        "nh3": 0.77
    },
    "2022-06-04 02:41:00": {
        "weather_code": 804,
        "temperature_celcius": 13.29,
        "dewpoint_celcius": 138.84,
        "1_hour_precipitation_percentage": 0.0,
        "clouds_percentage": 100,
        "relative_humidity_percentage": 74,
        "pressure_hpa": 1020,
        "wind_speed_mps": 6.69,
        "visibility_km": 10.0,
        "sunrise_hour": 3,
        "sunset_hour": 20,
        "1_hour_snow_percentage": 0.0,
        "aqi": 2,
        "pm2_5": 4.83,
        "pm10": 6.96,
        "so2": 1.97,
        "no": 0,
        "no2": 2.91,
        "co": 185.25,
        "o3": 92.98,
        "nh3": 0.77
    },
    "2022-06-04 02:46:00": {
        "weather_code": 804,
        "temperature_celcius": 13.25,
        "dewpoint_celcius": 138.93,
        "1_hour_precipitation_percentage": 0.0,
        "clouds_percentage": 100,
        "relative_humidity_percentage": 75,
        "pressure_hpa": 1020,
        "wind_speed_mps": 6.69,
        "visibility_km": 10.0,
        "sunrise_hour": 3,
        "sunset_hour": 20,
        "1_hour_snow_percentage": 0.0,
        "aqi": 2,
        "pm2_5": 4.83,
        "pm10": 6.96,
        "so2": 1.97,
        "no": 0,
        "no2": 2.91,
        "co": 185.25,
        "o3": 92.98,
        "nh3": 0.77
    },
    "2022-06-04 02:51:00": {
        "weather_code": 804,
        "temperature_celcius": 13.17,
        "dewpoint_celcius": 138.88,
        "1_hour_precipitation_percentage": 0.0,
        "clouds_percentage": 100,
        "relative_humidity_percentage": 75,
        "pressure_hpa": 1020,
        "wind_speed_mps": 6.69,
        "visibility_km": 10.0,
        "sunrise_hour": 3,
        "sunset_hour": 20,
        "1_hour_snow_percentage": 0.0,
        "aqi": 2,
        "pm2_5": 4.83,
        "pm10": 6.96,
        "so2": 1.97,
        "no": 0,
        "no2": 2.91,
        "co": 185.25,
        "o3": 92.98,
        "nh3": 0.77
    },
    "2022-06-04 02:56:00": {
        "weather_code": 804,
        "temperature_celcius": 13.17,
        "dewpoint_celcius": 138.88,
        "1_hour_precipitation_percentage": 0.0,
        "clouds_percentage": 100,
        "relative_humidity_percentage": 75,
        "pressure_hpa": 1020,
        "wind_speed_mps": 6.69,
        "visibility_km": 10.0,
        "sunrise_hour": 3,
        "sunset_hour": 20,
        "1_hour_snow_percentage": 0.0,
        "aqi": 2,
        "pm2_5": 4.83,
        "pm10": 6.96,
        "so2": 1.97,
        "no": 0,
        "no2": 2.91,
        "co": 185.25,
        "o3": 92.98,
        "nh3": 0.77
    },
    "2022-06-04 03:01:00": {
        "weather_code": 804,
        "temperature_celcius": 13.04,
        "dewpoint_celcius": 138.92,
        "1_hour_precipitation_percentage": 0.0,
        "clouds_percentage": 100,
        "relative_humidity_percentage": 76,
        "pressure_hpa": 1020,
        "wind_speed_mps": 5.66,
        "visibility_km": 10.0,
        "sunrise_hour": 3,
        "sunset_hour": 20,
        "1_hour_snow_percentage": 0.0,
        "aqi": 2,
        "pm2_5": 4.83,
        "pm10": 6.96,
        "so2": 1.97,
        "no": 0,
        "no2": 2.91,
        "co": 185.25,
        "o3": 92.98,
        "nh3": 0.77
    },
    "2022-06-04 03:06:00": {
        "weather_code": 804,
        "temperature_celcius": 13.04,
        "dewpoint_celcius": 138.92,
        "1_hour_precipitation_percentage": 0.0,
        "clouds_percentage": 100,
        "relative_humidity_percentage": 76,
        "pressure_hpa": 1020,
        "wind_speed_mps": 5.66,
        "visibility_km": 10.0,
        "sunrise_hour": 3,
        "sunset_hour": 20,
        "1_hour_snow_percentage": 0.0,
        "aqi": 2,
        "pm2_5": 4.83,
        "pm10": 6.96,
        "so2": 1.97,
        "no": 0,
        "no2": 2.91,
        "co": 185.25,
        "o3": 92.98,
        "nh3": 0.77
    },
    "2022-06-04 03:11:00": {
        "weather_code": 804,
        "temperature_celcius": 13.02,
        "dewpoint_celcius": 138.91,
        "1_hour_precipitation_percentage": 0.0,
        "clouds_percentage": 100,
        "relative_humidity_percentage": 76,
        "pressure_hpa": 1020,
        "wind_speed_mps": 5.66,
        "visibility_km": 10.0,
        "sunrise_hour": 3,
        "sunset_hour": 20,
        "1_hour_snow_percentage": 0.0,
        "aqi": 2,
        "pm2_5": 4.83,
        "pm10": 6.96,
        "so2": 1.97,
        "no": 0,
        "no2": 2.91,
        "co": 185.25,
        "o3": 92.98,
        "nh3": 0.77
    },
    "2022-06-04 03:16:00": {
        "weather_code": 804,
        "temperature_celcius": 12.95,
        "dewpoint_celcius": 138.98,
        "1_hour_precipitation_percentage": 0.0,
        "clouds_percentage": 100,
        "relative_humidity_percentage": 77,
        "pressure_hpa": 1020,
        "wind_speed_mps": 5.66,
        "visibility_km": 10.0,
        "sunrise_hour": 3,
        "sunset_hour": 20,
        "1_hour_snow_percentage": 0.0,
        "aqi": 2,
        "pm2_5": 4.83,
        "pm10": 6.96,
        "so2": 1.97,
        "no": 0,
        "no2": 2.91,
        "co": 185.25,
        "o3": 92.98,
        "nh3": 0.77
    },
    "2022-06-04 03:21:00": {
        "weather_code": 804,
        "temperature_celcius": 12.9,
        "dewpoint_celcius": 138.96,
        "1_hour_precipitation_percentage": 0.0,
        "clouds_percentage": 100,
        "relative_humidity_percentage": 77,
        "pressure_hpa": 1020,
        "wind_speed_mps": 5.66,
        "visibility_km": 10.0,
        "sunrise_hour": 3,
        "sunset_hour": 20,
        "1_hour_snow_percentage": 0.0,
        "aqi": 2,
        "pm2_5": 4.83,
        "pm10": 6.96,
        "so2": 1.97,
        "no": 0,
        "no2": 2.91,
        "co": 185.25,
        "o3": 92.98,
        "nh3": 0.77
    },
    "2022-06-04 03:26:00": {
        "weather_code": 804,
        "temperature_celcius": 12.9,
        "dewpoint_celcius": 138.96,
        "1_hour_precipitation_percentage": 0.0,
        "clouds_percentage": 100,
        "relative_humidity_percentage": 77,
        "pressure_hpa": 1020,
        "wind_speed_mps": 5.66,
        "visibility_km": 10.0,
        "sunrise_hour": 3,
        "sunset_hour": 20,
        "1_hour_snow_percentage": 0.0,
        "aqi": 2,
        "pm2_5": 4.83,
        "pm10": 6.96,
        "so2": 1.97,
        "no": 0,
        "no2": 2.91,
        "co": 185.25,
        "o3": 92.98,
        "nh3": 0.77
    },
    "2022-06-04 03:31:00": {
        "weather_code": 801,
        "temperature_celcius": 12.88,
        "dewpoint_celcius": 138.94,
        "1_hour_precipitation_percentage": 0.0,
        "clouds_percentage": 20,
        "relative_humidity_percentage": 77,
        "pressure_hpa": 1020,
        "wind_speed_mps": 4.63,
        "visibility_km": 10.0,
        "sunrise_hour": 3,
        "sunset_hour": 20,
        "1_hour_snow_percentage": 0.0,
        "aqi": 2,
        "pm2_5": 4.18,
        "pm10": 6.15,
        "so2": 1.91,
        "no": 0,
        "no2": 2.72,
        "co": 185.25,
        "o3": 90.84,
        "nh3": 0.65
    },
    "2022-06-04 03:36:00": {
        "weather_code": 801,
        "temperature_celcius": 12.86,
        "dewpoint_celcius": 139.04,
        "1_hour_precipitation_percentage": 0.0,
        "clouds_percentage": 20,
        "relative_humidity_percentage": 78,
        "pressure_hpa": 1020,
        "wind_speed_mps": 4.63,
        "visibility_km": 10.0,
        "sunrise_hour": 3,
        "sunset_hour": 20,
        "1_hour_snow_percentage": 0.0,
        "aqi": 2,
        "pm2_5": 4.18,
        "pm10": 6.15,
        "so2": 1.91,
        "no": 0,
        "no2": 2.72,
        "co": 185.25,
        "o3": 90.84,
        "nh3": 0.65
    },
    "2022-06-04 03:41:00": {
        "weather_code": 801,
        "temperature_celcius": 12.86,
        "dewpoint_celcius": 139.04,
        "1_hour_precipitation_percentage": 0.0,
        "clouds_percentage": 20,
        "relative_humidity_percentage": 78,
        "pressure_hpa": 1020,
        "wind_speed_mps": 4.63,
        "visibility_km": 10.0,
        "sunrise_hour": 3,
        "sunset_hour": 20,
        "1_hour_snow_percentage": 0.0,
        "aqi": 2,
        "pm2_5": 4.18,
        "pm10": 6.15,
        "so2": 1.91,
        "no": 0,
        "no2": 2.72,
        "co": 185.25,
        "o3": 90.84,
        "nh3": 0.65
    },
    "2022-06-04 03:46:00": {
        "weather_code": 801,
        "temperature_celcius": 12.85,
        "dewpoint_celcius": 139.03,
        "1_hour_precipitation_percentage": 0.0,
        "clouds_percentage": 20,
        "relative_humidity_percentage": 78,
        "pressure_hpa": 1020,
        "wind_speed_mps": 4.63,
        "visibility_km": 10.0,
        "sunrise_hour": 3,
        "sunset_hour": 20,
        "1_hour_snow_percentage": 0.0,
        "aqi": 2,
        "pm2_5": 4.18,
        "pm10": 6.15,
        "so2": 1.91,
        "no": 0,
        "no2": 2.72,
        "co": 185.25,
        "o3": 90.84,
        "nh3": 0.65
    },
    "2022-06-04 03:51:00": {
        "weather_code": 801,
        "temperature_celcius": 12.82,
        "dewpoint_celcius": 139.02,
        "1_hour_precipitation_percentage": 0.0,
        "clouds_percentage": 20,
        "relative_humidity_percentage": 78,
        "pressure_hpa": 1020,
        "wind_speed_mps": 4.63,
        "visibility_km": 10.0,
        "sunrise_hour": 3,
        "sunset_hour": 20,
        "1_hour_snow_percentage": 0.0,
        "aqi": 2,
        "pm2_5": 4.18,
        "pm10": 6.15,
        "so2": 1.91,
        "no": 0,
        "no2": 2.72,
        "co": 185.25,
        "o3": 90.84,
        "nh3": 0.65
    },
    "2022-06-04 03:56:00": {
        "weather_code": 801,
        "temperature_celcius": 12.79,
        "dewpoint_celcius": 139.0,
        "1_hour_precipitation_percentage": 0.0,
        "clouds_percentage": 20,
        "relative_humidity_percentage": 78,
        "pressure_hpa": 1020,
        "wind_speed_mps": 4.63,
        "visibility_km": 10.0,
        "sunrise_hour": 3,
        "sunset_hour": 20,
        "1_hour_snow_percentage": 0.0,
        "aqi": 2,
        "pm2_5": 4.18,
        "pm10": 6.15,
        "so2": 1.91,
        "no": 0,
        "no2": 2.72,
        "co": 185.25,
        "o3": 90.84,
        "nh3": 0.65
    },
    "2022-06-04 04:01:00": {
        "weather_code": 803,
        "temperature_celcius": 12.78,
        "dewpoint_celcius": 139.0,
        "1_hour_precipitation_percentage": 0.0,
        "clouds_percentage": 75,
        "relative_humidity_percentage": 78,
        "pressure_hpa": 1020,
        "wind_speed_mps": 3.6,
        "visibility_km": 10.0,
        "sunrise_hour": 3,
        "sunset_hour": 20,
        "1_hour_snow_percentage": 0.0,
        "aqi": 2,
        "pm2_5": 4.18,
        "pm10": 6.15,
        "so2": 1.91,
        "no": 0,
        "no2": 2.72,
        "co": 185.25,
        "o3": 90.84,
        "nh3": 0.65
    },
    "2022-06-04 04:06:00": {
        "weather_code": 803,
        "temperature_celcius": 12.79,
        "dewpoint_celcius": 139.11,
        "1_hour_precipitation_percentage": 0.0,
        "clouds_percentage": 75,
        "relative_humidity_percentage": 79,
        "pressure_hpa": 1020,
        "wind_speed_mps": 3.6,
        "visibility_km": 10.0,
        "sunrise_hour": 3,
        "sunset_hour": 20,
        "1_hour_snow_percentage": 0.0,
        "aqi": 2,
        "pm2_5": 4.18,
        "pm10": 6.15,
        "so2": 1.91,
        "no": 0,
        "no2": 2.72,
        "co": 185.25,
        "o3": 90.84,
        "nh3": 0.65
    },
    "2022-06-04 04:11:00": {
        "weather_code": 803,
        "temperature_celcius": 12.79,
        "dewpoint_celcius": 139.11,
        "1_hour_precipitation_percentage": 0.0,
        "clouds_percentage": 75,
        "relative_humidity_percentage": 79,
        "pressure_hpa": 1020,
        "wind_speed_mps": 3.6,
        "visibility_km": 10.0,
        "sunrise_hour": 3,
        "sunset_hour": 20,
        "1_hour_snow_percentage": 0.0,
        "aqi": 2,
        "pm2_5": 4.18,
        "pm10": 6.15,
        "so2": 1.91,
        "no": 0,
        "no2": 2.72,
        "co": 185.25,
        "o3": 90.84,
        "nh3": 0.65
    },
    "2022-06-04 04:16:00": {
        "weather_code": 803,
        "temperature_celcius": 12.72,
        "dewpoint_celcius": 139.07,
        "1_hour_precipitation_percentage": 0.0,
        "clouds_percentage": 75,
        "relative_humidity_percentage": 79,
        "pressure_hpa": 1020,
        "wind_speed_mps": 3.6,
        "visibility_km": 10.0,
        "sunrise_hour": 3,
        "sunset_hour": 20,
        "1_hour_snow_percentage": 0.0,
        "aqi": 2,
        "pm2_5": 4.18,
        "pm10": 6.15,
        "so2": 1.91,
        "no": 0,
        "no2": 2.72,
        "co": 185.25,
        "o3": 90.84,
        "nh3": 0.65
    },
    "2022-06-04 04:21:00": {
        "weather_code": 803,
        "temperature_celcius": 12.72,
        "dewpoint_celcius": 139.07,
        "1_hour_precipitation_percentage": 0.0,
        "clouds_percentage": 75,
        "relative_humidity_percentage": 79,
        "pressure_hpa": 1020,
        "wind_speed_mps": 3.6,
        "visibility_km": 10.0,
        "sunrise_hour": 3,
        "sunset_hour": 20,
        "1_hour_snow_percentage": 0.0,
        "aqi": 2,
        "pm2_5": 4.18,
        "pm10": 6.15,
        "so2": 1.91,
        "no": 0,
        "no2": 2.72,
        "co": 185.25,
        "o3": 90.84,
        "nh3": 0.65
    },
    "2022-06-04 04:26:00": {
        "weather_code": 803,
        "temperature_celcius": 12.69,
        "dewpoint_celcius": 139.16,
        "1_hour_precipitation_percentage": 0.0,
        "clouds_percentage": 75,
        "relative_humidity_percentage": 80,
        "pressure_hpa": 1020,
        "wind_speed_mps": 3.6,
        "visibility_km": 10.0,
        "sunrise_hour": 3,
        "sunset_hour": 20,
        "1_hour_snow_percentage": 0.0,
        "aqi": 2,
        "pm2_5": 4.18,
        "pm10": 6.15,
        "so2": 1.91,
        "no": 0,
        "no2": 2.72,
        "co": 185.25,
        "o3": 90.84,
        "nh3": 0.65
    },
    "2022-06-04 04:31:00": {
        "weather_code": 803,
        "temperature_celcius": 12.67,
        "dewpoint_celcius": 139.14,
        "1_hour_precipitation_percentage": 0.0,
        "clouds_percentage": 75,
        "relative_humidity_percentage": 80,
        "pressure_hpa": 1020,
        "wind_speed_mps": 4.63,
        "visibility_km": 10.0,
        "sunrise_hour": 3,
        "sunset_hour": 20,
        "1_hour_snow_percentage": 0.0,
        "aqi": 2,
        "pm2_5": 4.18,
        "pm10": 6.15,
        "so2": 1.91,
        "no": 0,
        "no2": 2.72,
        "co": 185.25,
        "o3": 90.84,
        "nh3": 0.65
    },
    "2022-06-04 04:36:00": {
        "weather_code": 803,
        "temperature_celcius": 12.65,
        "dewpoint_celcius": 139.13,
        "1_hour_precipitation_percentage": 0.0,
        "clouds_percentage": 75,
        "relative_humidity_percentage": 80,
        "pressure_hpa": 1020,
        "wind_speed_mps": 4.63,
        "visibility_km": 10.0,
        "sunrise_hour": 3,
        "sunset_hour": 20,
        "1_hour_snow_percentage": 0.0,
        "aqi": 2,
        "pm2_5": 3.83,
        "pm10": 5.55,
        "so2": 1.88,
        "no": 0,
        "no2": 2.7,
        "co": 185.25,
        "o3": 88.69,
        "nh3": 0.49
    },
    "2022-06-04 04:41:00": {
        "weather_code": 803,
        "temperature_celcius": 12.63,
        "dewpoint_celcius": 139.12,
        "1_hour_precipitation_percentage": 0.0,
        "clouds_percentage": 75,
        "relative_humidity_percentage": 80,
        "pressure_hpa": 1020,
        "wind_speed_mps": 4.63,
        "visibility_km": 10.0,
        "sunrise_hour": 3,
        "sunset_hour": 20,
        "1_hour_snow_percentage": 0.0,
        "aqi": 2,
        "pm2_5": 3.83,
        "pm10": 5.55,
        "so2": 1.88,
        "no": 0,
        "no2": 2.7,
        "co": 185.25,
        "o3": 88.69,
        "nh3": 0.49
    },
    "2022-06-04 04:46:00": {
        "weather_code": 803,
        "temperature_celcius": 12.63,
        "dewpoint_celcius": 139.12,
        "1_hour_precipitation_percentage": 0.0,
        "clouds_percentage": 75,
        "relative_humidity_percentage": 80,
        "pressure_hpa": 1020,
        "wind_speed_mps": 4.63,
        "visibility_km": 10.0,
        "sunrise_hour": 3,
        "sunset_hour": 20,
        "1_hour_snow_percentage": 0.0,
        "aqi": 2,
        "pm2_5": 3.83,
        "pm10": 5.55,
        "so2": 1.88,
        "no": 0,
        "no2": 2.7,
        "co": 185.25,
        "o3": 88.69,
        "nh3": 0.49
    },
    "2022-06-04 04:51:00": {
        "weather_code": 803,
        "temperature_celcius": 12.58,
        "dewpoint_celcius": 139.1,
        "1_hour_precipitation_percentage": 0.0,
        "clouds_percentage": 75,
        "relative_humidity_percentage": 80,
        "pressure_hpa": 1020,
        "wind_speed_mps": 4.63,
        "visibility_km": 10.0,
        "sunrise_hour": 3,
        "sunset_hour": 20,
        "1_hour_snow_percentage": 0.0,
        "aqi": 2,
        "pm2_5": 3.83,
        "pm10": 5.55,
        "so2": 1.88,
        "no": 0,
        "no2": 2.7,
        "co": 185.25,
        "o3": 88.69,
        "nh3": 0.49
    },
    "2022-06-04 04:56:00": {
        "weather_code": 803,
        "temperature_celcius": 12.58,
        "dewpoint_celcius": 139.1,
        "1_hour_precipitation_percentage": 0.0,
        "clouds_percentage": 75,
        "relative_humidity_percentage": 80,
        "pressure_hpa": 1020,
        "wind_speed_mps": 4.63,
        "visibility_km": 10.0,
        "sunrise_hour": 3,
        "sunset_hour": 20,
        "1_hour_snow_percentage": 0.0,
        "aqi": 2,
        "pm2_5": 3.83,
        "pm10": 5.55,
        "so2": 1.88,
        "no": 0,
        "no2": 2.7,
        "co": 185.25,
        "o3": 88.69,
        "nh3": 0.49
    },
    "2022-06-04 05:01:00": {
        "weather_code": 802,
        "temperature_celcius": 12.58,
        "dewpoint_celcius": 139.1,
        "1_hour_precipitation_percentage": 0.0,
        "clouds_percentage": 40,
        "relative_humidity_percentage": 80,
        "pressure_hpa": 1020,
        "wind_speed_mps": 4.63,
        "visibility_km": 10.0,
        "sunrise_hour": 3,
        "sunset_hour": 20,
        "1_hour_snow_percentage": 0.0,
        "aqi": 2,
        "pm2_5": 3.83,
        "pm10": 5.55,
        "so2": 1.88,
        "no": 0,
        "no2": 2.7,
        "co": 185.25,
        "o3": 88.69,
        "nh3": 0.49
    },
    "2022-06-04 05:06:00": {
        "weather_code": 802,
        "temperature_celcius": 12.57,
        "dewpoint_celcius": 139.09,
        "1_hour_precipitation_percentage": 0.0,
        "clouds_percentage": 40,
        "relative_humidity_percentage": 80,
        "pressure_hpa": 1020,
        "wind_speed_mps": 4.63,
        "visibility_km": 10.0,
        "sunrise_hour": 3,
        "sunset_hour": 20,
        "1_hour_snow_percentage": 0.0,
        "aqi": 2,
        "pm2_5": 3.83,
        "pm10": 5.55,
        "so2": 1.88,
        "no": 0,
        "no2": 2.7,
        "co": 185.25,
        "o3": 88.69,
        "nh3": 0.49
    },
    "2022-06-04 05:11:00": {
        "weather_code": 802,
        "temperature_celcius": 12.57,
        "dewpoint_celcius": 139.09,
        "1_hour_precipitation_percentage": 0.0,
        "clouds_percentage": 40,
        "relative_humidity_percentage": 80,
        "pressure_hpa": 1020,
        "wind_speed_mps": 4.63,
        "visibility_km": 10.0,
        "sunrise_hour": 3,
        "sunset_hour": 20,
        "1_hour_snow_percentage": 0.0,
        "aqi": 2,
        "pm2_5": 3.83,
        "pm10": 5.55,
        "so2": 1.88,
        "no": 0,
        "no2": 2.7,
        "co": 185.25,
        "o3": 88.69,
        "nh3": 0.49
    },
    "2022-06-04 05:16:00": {
        "weather_code": 802,
        "temperature_celcius": 12.58,
        "dewpoint_celcius": 139.1,
        "1_hour_precipitation_percentage": 0.0,
        "clouds_percentage": 40,
        "relative_humidity_percentage": 80,
        "pressure_hpa": 1020,
        "wind_speed_mps": 4.63,
        "visibility_km": 10.0,
        "sunrise_hour": 3,
        "sunset_hour": 20,
        "1_hour_snow_percentage": 0.0,
        "aqi": 2,
        "pm2_5": 3.83,
        "pm10": 5.55,
        "so2": 1.88,
        "no": 0,
        "no2": 2.7,
        "co": 185.25,
        "o3": 88.69,
        "nh3": 0.49
    },
    "2022-06-04 05:21:00": {
        "weather_code": 802,
        "temperature_celcius": 12.58,
        "dewpoint_celcius": 139.1,
        "1_hour_precipitation_percentage": 0.0,
        "clouds_percentage": 40,
        "relative_humidity_percentage": 80,
        "pressure_hpa": 1020,
        "wind_speed_mps": 4.63,
        "visibility_km": 10.0,
        "sunrise_hour": 3,
        "sunset_hour": 20,
        "1_hour_snow_percentage": 0.0,
        "aqi": 2,
        "pm2_5": 3.83,
        "pm10": 5.55,
        "so2": 1.88,
        "no": 0,
        "no2": 2.7,
        "co": 185.25,
        "o3": 88.69,
        "nh3": 0.49
    },
    "2022-06-04 05:26:00": {
        "weather_code": 802,
        "temperature_celcius": 12.58,
        "dewpoint_celcius": 139.1,
        "1_hour_precipitation_percentage": 0.0,
        "clouds_percentage": 40,
        "relative_humidity_percentage": 80,
        "pressure_hpa": 1020,
        "wind_speed_mps": 4.63,
        "visibility_km": 10.0,
        "sunrise_hour": 3,
        "sunset_hour": 20,
        "1_hour_snow_percentage": 0.0,
        "aqi": 2,
        "pm2_5": 3.91,
        "pm10": 5.86,
        "so2": 2,
        "no": 0,
        "no2": 3.04,
        "co": 186.92,
        "o3": 83.69,
        "nh3": 0.41
    },
    "2022-06-04 05:31:00": {
        "weather_code": 802,
        "temperature_celcius": 12.59,
        "dewpoint_celcius": 139.11,
        "1_hour_precipitation_percentage": 0.0,
        "clouds_percentage": 40,
        "relative_humidity_percentage": 80,
        "pressure_hpa": 1020,
        "wind_speed_mps": 4.12,
        "visibility_km": 10.0,
        "sunrise_hour": 3,
        "sunset_hour": 20,
        "1_hour_snow_percentage": 0.0,
        "aqi": 2,
        "pm2_5": 3.91,
        "pm10": 5.86,
        "so2": 2,
        "no": 0,
        "no2": 3.04,
        "co": 186.92,
        "o3": 83.69,
        "nh3": 0.41
    },
    "2022-06-04 05:36:00": {
        "weather_code": 802,
        "temperature_celcius": 12.59,
        "dewpoint_celcius": 139.21,
        "1_hour_precipitation_percentage": 0.0,
        "clouds_percentage": 40,
        "relative_humidity_percentage": 81,
        "pressure_hpa": 1020,
        "wind_speed_mps": 4.12,
        "visibility_km": 10.0,
        "sunrise_hour": 3,
        "sunset_hour": 20,
        "1_hour_snow_percentage": 0.0,
        "aqi": 2,
        "pm2_5": 3.91,
        "pm10": 5.86,
        "so2": 2,
        "no": 0,
        "no2": 3.04,
        "co": 186.92,
        "o3": 83.69,
        "nh3": 0.41
    },
    "2022-06-04 05:41:00": {
        "weather_code": 802,
        "temperature_celcius": 12.63,
        "dewpoint_celcius": 139.23,
        "1_hour_precipitation_percentage": 0.0,
        "clouds_percentage": 40,
        "relative_humidity_percentage": 81,
        "pressure_hpa": 1020,
        "wind_speed_mps": 4.12,
        "visibility_km": 10.0,
        "sunrise_hour": 3,
        "sunset_hour": 20,
        "1_hour_snow_percentage": 0.0,
        "aqi": 2,
        "pm2_5": 3.91,
        "pm10": 5.86,
        "so2": 2,
        "no": 0,
        "no2": 3.04,
        "co": 186.92,
        "o3": 83.69,
        "nh3": 0.41
    },
    "2022-06-04 05:46:00": {
        "weather_code": 802,
        "temperature_celcius": 12.65,
        "dewpoint_celcius": 139.24,
        "1_hour_precipitation_percentage": 0.0,
        "clouds_percentage": 40,
        "relative_humidity_percentage": 81,
        "pressure_hpa": 1020,
        "wind_speed_mps": 4.12,
        "visibility_km": 10.0,
        "sunrise_hour": 3,
        "sunset_hour": 20,
        "1_hour_snow_percentage": 0.0,
        "aqi": 2,
        "pm2_5": 3.91,
        "pm10": 5.86,
        "so2": 2,
        "no": 0,
        "no2": 3.04,
        "co": 186.92,
        "o3": 83.69,
        "nh3": 0.41
    },
    "2022-06-04 05:51:00": {
        "weather_code": 802,
        "temperature_celcius": 12.68,
        "dewpoint_celcius": 139.15,
        "1_hour_precipitation_percentage": 0.0,
        "clouds_percentage": 40,
        "relative_humidity_percentage": 80,
        "pressure_hpa": 1020,
        "wind_speed_mps": 4.12,
        "visibility_km": 10.0,
        "sunrise_hour": 3,
        "sunset_hour": 20,
        "1_hour_snow_percentage": 0.0,
        "aqi": 2,
        "pm2_5": 3.91,
        "pm10": 5.86,
        "so2": 2,
        "no": 0,
        "no2": 3.04,
        "co": 186.92,
        "o3": 83.69,
        "nh3": 0.41
    },
    "2022-06-04 05:56:00": {
        "weather_code": 802,
        "temperature_celcius": 12.68,
        "dewpoint_celcius": 139.15,
        "1_hour_precipitation_percentage": 0.0,
        "clouds_percentage": 40,
        "relative_humidity_percentage": 80,
        "pressure_hpa": 1020,
        "wind_speed_mps": 4.12,
        "visibility_km": 10.0,
        "sunrise_hour": 3,
        "sunset_hour": 20,
        "1_hour_snow_percentage": 0.0,
        "aqi": 2,
        "pm2_5": 3.91,
        "pm10": 5.86,
        "so2": 2,
        "no": 0,
        "no2": 3.04,
        "co": 186.92,
        "o3": 83.69,
        "nh3": 0.41
    },
    "2022-06-04 06:01:00": {
        "weather_code": 803,
        "temperature_celcius": 12.68,
        "dewpoint_celcius": 139.15,
        "1_hour_precipitation_percentage": 0.0,
        "clouds_percentage": 75,
        "relative_humidity_percentage": 80,
        "pressure_hpa": 1020,
        "wind_speed_mps": 4.63,
        "visibility_km": 10.0,
        "sunrise_hour": 3,
        "sunset_hour": 20,
        "1_hour_snow_percentage": 0.0,
        "aqi": 2,
        "pm2_5": 3.91,
        "pm10": 5.86,
        "so2": 2,
        "no": 0,
        "no2": 3.04,
        "co": 186.92,
        "o3": 83.69,
        "nh3": 0.41
    },
    "2022-06-04 06:06:00": {
        "weather_code": 803,
        "temperature_celcius": 12.69,
        "dewpoint_celcius": 139.16,
        "1_hour_precipitation_percentage": 0.0,
        "clouds_percentage": 75,
        "relative_humidity_percentage": 80,
        "pressure_hpa": 1020,
        "wind_speed_mps": 4.63,
        "visibility_km": 10.0,
        "sunrise_hour": 3,
        "sunset_hour": 20,
        "1_hour_snow_percentage": 0.0,
        "aqi": 2,
        "pm2_5": 3.91,
        "pm10": 5.86,
        "so2": 2,
        "no": 0,
        "no2": 3.04,
        "co": 186.92,
        "o3": 83.69,
        "nh3": 0.41
    },
    "2022-06-04 06:11:00": {
        "weather_code": 803,
        "temperature_celcius": 12.69,
        "dewpoint_celcius": 139.16,
        "1_hour_precipitation_percentage": 0.0,
        "clouds_percentage": 75,
        "relative_humidity_percentage": 80,
        "pressure_hpa": 1020,
        "wind_speed_mps": 4.63,
        "visibility_km": 10.0,
        "sunrise_hour": 3,
        "sunset_hour": 20,
        "1_hour_snow_percentage": 0.0,
        "aqi": 2,
        "pm2_5": 3.91,
        "pm10": 5.86,
        "so2": 2,
        "no": 0,
        "no2": 3.04,
        "co": 186.92,
        "o3": 83.69,
        "nh3": 0.41
    },
    "2022-06-04 06:16:00": {
        "weather_code": 803,
        "temperature_celcius": 12.6,
        "dewpoint_celcius": 139.11,
        "1_hour_precipitation_percentage": 0.0,
        "clouds_percentage": 75,
        "relative_humidity_percentage": 80,
        "pressure_hpa": 1020,
        "wind_speed_mps": 4.63,
        "visibility_km": 10.0,
        "sunrise_hour": 3,
        "sunset_hour": 20,
        "1_hour_snow_percentage": 0.0,
        "aqi": 2,
        "pm2_5": 3.91,
        "pm10": 5.86,
        "so2": 2,
        "no": 0,
        "no2": 3.04,
        "co": 186.92,
        "o3": 83.69,
        "nh3": 0.41
    },
    "2022-06-04 06:21:00": {
        "weather_code": 803,
        "temperature_celcius": 12.55,
        "dewpoint_celcius": 139.08,
        "1_hour_precipitation_percentage": 0.0,
        "clouds_percentage": 75,
        "relative_humidity_percentage": 80,
        "pressure_hpa": 1020,
        "wind_speed_mps": 4.63,
        "visibility_km": 10.0,
        "sunrise_hour": 3,
        "sunset_hour": 20,
        "1_hour_snow_percentage": 0.0,
        "aqi": 2,
        "pm2_5": 3.91,
        "pm10": 5.86,
        "so2": 2,
        "no": 0,
        "no2": 3.04,
        "co": 186.92,
        "o3": 83.69,
        "nh3": 0.41
    },
    "2022-06-04 06:26:00": {
        "weather_code": 803,
        "temperature_celcius": 12.6,
        "dewpoint_celcius": 139.11,
        "1_hour_precipitation_percentage": 0.0,
        "clouds_percentage": 75,
        "relative_humidity_percentage": 80,
        "pressure_hpa": 1020,
        "wind_speed_mps": 4.63,
        "visibility_km": 10.0,
        "sunrise_hour": 3,
        "sunset_hour": 20,
        "1_hour_snow_percentage": 0.0,
        "aqi": 2,
        "pm2_5": 3.91,
        "pm10": 5.86,
        "so2": 2,
        "no": 0,
        "no2": 3.04,
        "co": 186.92,
        "o3": 83.69,
        "nh3": 0.41
    },
    "2022-06-04 06:31:00": {
        "weather_code": 803,
        "temperature_celcius": 12.59,
        "dewpoint_celcius": 139.11,
        "1_hour_precipitation_percentage": 0.0,
        "clouds_percentage": 75,
        "relative_humidity_percentage": 80,
        "pressure_hpa": 1020,
        "wind_speed_mps": 4.63,
        "visibility_km": 10.0,
        "sunrise_hour": 3,
        "sunset_hour": 20,
        "1_hour_snow_percentage": 0.0,
        "aqi": 1,
        "pm2_5": 3.83,
        "pm10": 5.66,
        "so2": 2.24,
        "no": 0.02,
        "no2": 4.58,
        "co": 188.59,
        "o3": 76.53,
        "nh3": 0.41
    },
    "2022-06-04 06:36:00": {
        "weather_code": 803,
        "temperature_celcius": 12.58,
        "dewpoint_celcius": 139.1,
        "1_hour_precipitation_percentage": 0.0,
        "clouds_percentage": 75,
        "relative_humidity_percentage": 80,
        "pressure_hpa": 1020,
        "wind_speed_mps": 4.63,
        "visibility_km": 10.0,
        "sunrise_hour": 3,
        "sunset_hour": 20,
        "1_hour_snow_percentage": 0.0,
        "aqi": 1,
        "pm2_5": 3.83,
        "pm10": 5.66,
        "so2": 2.24,
        "no": 0.02,
        "no2": 4.58,
        "co": 188.59,
        "o3": 76.53,
        "nh3": 0.41
    },
    "2022-06-04 06:41:00": {
        "weather_code": 803,
        "temperature_celcius": 12.59,
        "dewpoint_celcius": 139.11,
        "1_hour_precipitation_percentage": 0.0,
        "clouds_percentage": 75,
        "relative_humidity_percentage": 80,
        "pressure_hpa": 1020,
        "wind_speed_mps": 4.63,
        "visibility_km": 10.0,
        "sunrise_hour": 3,
        "sunset_hour": 20,
        "1_hour_snow_percentage": 0.0,
        "aqi": 1,
        "pm2_5": 3.83,
        "pm10": 5.66,
        "so2": 2.24,
        "no": 0.02,
        "no2": 4.58,
        "co": 188.59,
        "o3": 76.53,
        "nh3": 0.41
    },
    "2022-06-04 06:46:00": {
        "weather_code": 803,
        "temperature_celcius": 12.61,
        "dewpoint_celcius": 139.12,
        "1_hour_precipitation_percentage": 0.0,
        "clouds_percentage": 75,
        "relative_humidity_percentage": 80,
        "pressure_hpa": 1020,
        "wind_speed_mps": 4.63,
        "visibility_km": 10.0,
        "sunrise_hour": 3,
        "sunset_hour": 20,
        "1_hour_snow_percentage": 0.0,
        "aqi": 1,
        "pm2_5": 3.83,
        "pm10": 5.66,
        "so2": 2.24,
        "no": 0.02,
        "no2": 4.58,
        "co": 188.59,
        "o3": 76.53,
        "nh3": 0.41
    },
    "2022-06-04 06:51:00": {
        "weather_code": 803,
        "temperature_celcius": 12.67,
        "dewpoint_celcius": 139.14,
        "1_hour_precipitation_percentage": 0.0,
        "clouds_percentage": 75,
        "relative_humidity_percentage": 80,
        "pressure_hpa": 1020,
        "wind_speed_mps": 4.63,
        "visibility_km": 10.0,
        "sunrise_hour": 3,
        "sunset_hour": 20,
        "1_hour_snow_percentage": 0.0,
        "aqi": 1,
        "pm2_5": 3.83,
        "pm10": 5.66,
        "so2": 2.24,
        "no": 0.02,
        "no2": 4.58,
        "co": 188.59,
        "o3": 76.53,
        "nh3": 0.41
    },
    "2022-06-04 06:56:00": {},
    "2022-06-04 07:01:00": {},
    "2022-06-04 07:06:00": {},
    "2022-06-04 07:11:00": {},
    "2022-06-04 07:16:00": {},
    "2022-06-04 07:21:00": {},
    "2022-06-04 07:26:00": {},
    "2022-06-04 07:31:00": {},
    "2022-06-04 07:36:00": {},
    "2022-06-04 07:41:00": {},
    "2022-06-04 07:46:00": {},
    "2022-06-04 07:51:00": {},
    "2022-06-04 07:56:00": {},
    "2022-06-04 08:01:00": {},
    "2022-06-04 08:06:00": {},
    "2022-06-04 08:11:00": {},
    "2022-06-04 08:16:00": {},
    "2022-06-04 08:21:00": {},
    "2022-06-04 08:26:00": {},
    "2022-06-04 08:31:00": {},
    "2022-06-04 08:36:00": {},
    "2022-06-04 08:41:00": {},
    "2022-06-04 08:46:00": {},
    "2022-06-04 08:51:00": {},
    "2022-06-04 08:56:00": {},
    "2022-06-04 09:01:00": {},
    "2022-06-04 09:06:00": {},
    "2022-06-04 09:11:00": {},
    "2022-06-04 09:16:00": {},
    "2022-06-04 09:21:00": {},
    "2022-06-04 09:26:00": {},
    "2022-06-04 09:31:00": {},
    "2022-06-04 09:36:00": {},
    "2022-06-04 09:41:00": {},
    "2022-06-04 09:46:00": {},
    "2022-06-04 09:51:00": {},
    "2022-06-04 09:56:00": {},
    "2022-06-04 10:01:00": {},
    "2022-06-04 10:06:00": {},
    "2022-06-04 10:11:00": {},
    "2022-06-04 10:16:00": {},
    "2022-06-04 10:21:00": {},
    "2022-06-04 10:26:00": {},
    "2022-06-04 10:31:00": {},
    "2022-06-04 10:36:00": {},
    "2022-06-04 10:41:00": {},
    "2022-06-04 10:46:00": {},
    "2022-06-04 10:51:00": {},
    "2022-06-04 10:56:00": {},
    "2022-06-04 11:01:00": {},
    "2022-06-04 11:06:00": {},
    "2022-06-04 11:11:00": {},
    "2022-06-04 11:16:00": {},
    "2022-06-04 11:21:00": {},
    "2022-06-04 11:26:00": {},
    "2022-06-04 11:31:00": {},
    "2022-06-04 11:36:00": {},
    "2022-06-04 11:41:00": {},
    "2022-06-04 11:46:00": {},
    "2022-06-04 11:51:00": {},
    "2022-06-04 11:56:00": {},
    "2022-06-04 12:01:00": {},
    "2022-06-04 12:06:00": {},
    "2022-06-04 12:11:00": {},
    "2022-06-04 12:16:00": {},
    "2022-06-04 12:21:00": {},
    "2022-06-04 12:26:00": {},
    "2022-06-04 12:31:00": {},
    "2022-06-04 12:36:00": {},
    "2022-06-04 12:41:00": {},
    "2022-06-04 12:46:00": {},
    "2022-06-04 12:51:00": {},
    "2022-06-04 12:56:00": {},
    "2022-06-04 13:01:00": {},
    "2022-06-04 13:06:00": {},
    "2022-06-04 13:11:00": {},
    "2022-06-04 13:16:00": {},
    "2022-06-04 13:21:00": {},
    "2022-06-04 13:26:00": {},
    "2022-06-04 13:31:00": {},
    "2022-06-04 13:36:00": {},
    "2022-06-04 13:41:00": {},
    "2022-06-04 13:46:00": {},
    "2022-06-04 13:51:00": {},
    "2022-06-04 13:56:00": {},
    "2022-06-04 14:01:00": {},
    "2022-06-04 14:06:00": {},
    "2022-06-04 14:11:00": {},
    "2022-06-04 14:16:00": {},
    "2022-06-04 14:21:00": {},
    "2022-06-04 14:26:00": {},
    "2022-06-04 14:31:00": {},
    "2022-06-04 14:36:00": {},
    "2022-06-04 14:41:00": {},
    "2022-06-04 14:46:00": {},
    "2022-06-04 14:51:00": {},
    "2022-06-04 14:56:00": {},
    "2022-06-04 15:01:00": {},
    "2022-06-04 15:06:00": {},
    "2022-06-04 15:11:00": {},
    "2022-06-04 15:16:00": {},
    "2022-06-04 15:21:00": {},
    "2022-06-04 15:26:00": {},
    "2022-06-04 15:31:00": {},
    "2022-06-04 15:36:00": {},
    "2022-06-04 15:41:00": {},
    "2022-06-04 15:46:00": {},
    "2022-06-04 15:51:00": {},
    "2022-06-04 15:56:00": {},
    "2022-06-04 16:01:00": {},
    "2022-06-04 16:06:00": {},
    "2022-06-04 16:11:00": {},
    "2022-06-04 16:16:00": {},
    "2022-06-04 16:21:00": {},
    "2022-06-04 16:26:00": {},
    "2022-06-04 16:31:00": {},
    "2022-06-04 16:36:00": {},
    "2022-06-04 16:41:00": {},
    "2022-06-04 16:46:00": {},
    "2022-06-04 16:51:00": {},
    "2022-06-04 16:56:00": {},
    "2022-06-04 17:01:00": {},
    "2022-06-04 17:06:00": {},
    "2022-06-04 17:11:00": {},
    "2022-06-04 17:16:00": {},
    "2022-06-04 17:21:00": {},
    "2022-06-04 17:26:00": {},
    "2022-06-04 17:31:00": {},
    "2022-06-04 17:36:00": {},
    "2022-06-04 17:41:00": {},
    "2022-06-04 17:46:00": {},
    "2022-06-04 17:51:00": {},
    "2022-06-04 17:56:00": {},
    "2022-06-04 18:01:00": {},
    "2022-06-04 18:06:00": {},
    "2022-06-04 18:11:00": {},
    "2022-06-04 18:16:00": {},
    "2022-06-04 18:21:00": {},
    "2022-06-04 18:26:00": {},
    "2022-06-04 18:31:00": {},
    "2022-06-04 18:36:00": {},
    "2022-06-04 18:41:00": {},
    "2022-06-04 18:46:00": {},
    "2022-06-04 18:51:00": {},
    "2022-06-04 18:56:00": {},
    "2022-06-04 19:01:00": {},
    "2022-06-04 19:06:00": {},
    "2022-06-04 19:11:00": {},
    "2022-06-04 19:16:00": {},
    "2022-06-04 19:21:00": {},
    "2022-06-04 19:26:00": {},
    "2022-06-04 19:31:00": {},
    "2022-06-04 19:36:00": {},
    "2022-06-04 19:41:00": {},
    "2022-06-04 19:46:00": {},
    "2022-06-04 19:51:00": {},
    "2022-06-04 19:56:00": {},
    "2022-06-04 20:01:00": {},
    "2022-06-04 20:06:00": {},
    "2022-06-04 20:11:00": {},
    "2022-06-04 20:16:00": {},
    "2022-06-04 20:21:00": {},
    "2022-06-04 20:26:00": {},
    "2022-06-04 20:31:00": {},
    "2022-06-04 20:36:00": {},
    "2022-06-04 20:41:00": {},
    "2022-06-04 20:46:00": {},
    "2022-06-04 20:51:00": {},
    "2022-06-04 20:56:00": {},
    "2022-06-04 21:01:00": {},
    "2022-06-04 21:06:00": {},
    "2022-06-04 21:11:00": {},
    "2022-06-04 21:16:00": {},
    "2022-06-04 21:21:00": {},
    "2022-06-04 21:26:00": {},
    "2022-06-04 21:31:00": {},
    "2022-06-04 21:36:00": {},
    "2022-06-04 21:41:00": {},
    "2022-06-04 21:46:00": {},
    "2022-06-04 21:51:00": {},
    "2022-06-04 21:56:00": {},
    "2022-06-04 22:01:00": {},
    "2022-06-04 22:06:00": {},
    "2022-06-04 22:11:00": {},
    "2022-06-04 22:16:00": {},
    "2022-06-04 22:21:00": {},
    "2022-06-04 22:26:00": {},
    "2022-06-04 22:31:00": {},
    "2022-06-04 22:36:00": {},
    "2022-06-04 22:41:00": {},
    "2022-06-04 22:46:00": {},
    "2022-06-04 22:51:00": {},
    "2022-06-04 22:56:00": {},
    "2022-06-04 23:01:00": {},
    "2022-06-04 23:06:00": {},
    "2022-06-04 23:11:00": {},
    "2022-06-04 23:16:00": {},
    "2022-06-04 23:21:00": {},
    "2022-06-04 23:26:00": {},
    "2022-06-04 23:31:00": {},
    "2022-06-04 23:36:00": {},
    "2022-06-04 23:41:00": {},
    "2022-06-04 23:46:00": {},
    "2022-06-04 23:51:00": {}
}